kaque/__init__.py
kaque/graphs/__init__.py
kaque/graphs/data/__init__.py
kaque/graphs/data/data.py
kaque/graphs/data/nested.py
kaque/graphs/data/primitives.py
kaque/graphs/maps/__init__.py
kaque/graphs/maps/maps.py
kaque-0.0.0.dist-info/METADATA
kaque-0.0.0.dist-info/WHEEL
kaque-0.0.0.dist-info/RECORD
